pyCloudy/__init__.py
pyCloudy/version.py
pyCloudy/c1d/__init__.py
pyCloudy/c1d/cloudy_model.py
pyCloudy/c3d/__init__.py
pyCloudy/c3d/model_3d.py
pyCloudy/db/MdB.py
pyCloudy/db/__init__.py
pyCloudy/db/continuum_bands.ini
pyCloudy/db/initSQL.py
pyCloudy/db/use3MdB.py
pyCloudy/utils/Config.py
pyCloudy/utils/Izotov2013_CR.txt
pyCloudy/utils/__init__.py
pyCloudy/utils/astro.py
pyCloudy/utils/convert_c17_c13.txt
pyCloudy/utils/convert_c17_c13_2.txt
pyCloudy/utils/init.py
pyCloudy/utils/logging.py
pyCloudy/utils/misc.py
pyCloudy/utils/physics.py
pyCloudy/utils/pyneb2cloudy.txt
pyCloudy/utils/red_corr.py
pycloudy-0.9.16.dist-info/licenses/LICENSE.md
pycloudy-0.9.16.dist-info/METADATA
pycloudy-0.9.16.dist-info/WHEEL
pycloudy-0.9.16.dist-info/top_level.txt
pycloudy-0.9.16.dist-info/RECORD
