Metadata-Version: 2.4
Name: pyCloudy
Version: 0.9.16
Summary: Tools to manage Astronomical Cloudy photoionization code
Home-page: https://sites.google.com/site/pycloudy/
Download-URL: https://github.com/Morisset/pyCloudy/releases/tag/0.9.16
Author: Christophe Morisset IA-UNAM
Author-email: chris.morisset@gmail.com
Maintainer: Christophe Morisset IA-UNAM
Maintainer-email: chris.morisset@gmail.com
License: GPL
Keywords: astronomy photoionization cloudy
Classifier: Development Status :: 5 - Production/Stable
Classifier: Intended Audience :: Science/Research
Classifier: License :: Free for non-commercial use
Classifier: Programming Language :: Python :: 2
Classifier: Topic :: Scientific/Engineering :: Astronomy
License-File: LICENSE.md
Dynamic: author
Dynamic: author-email
Dynamic: classifier
Dynamic: description
Dynamic: download-url
Dynamic: home-page
Dynamic: keywords
Dynamic: license
Dynamic: license-file
Dynamic: maintainer
Dynamic: maintainer-email
Dynamic: summary
